canif/__init__.py
canif/canif.py
canif/cli.py
canif/lexer.py
canif/parser.py
canif/utils.py
canif/builder/__init__.py
canif/builder/base.py
canif/builder/jsonmixin.py
canif/builder/jsonprinter.py
canif/builder/pods.py
canif/builder/prettyprint.py
canif/builder/verbatim.py
canif-0.3.1.dist-info/LICENSE
canif-0.3.1.dist-info/METADATA
canif-0.3.1.dist-info/WHEEL
canif-0.3.1.dist-info/entry_points.txt
canif-0.3.1.dist-info/top_level.txt
canif-0.3.1.dist-info/RECORD
