Metadata-Version: 2.1
Name: canif
Version: 0.3.1
Summary: Parser and pretty-printer for JSON and JSON-ish data
Home-page: https://github.com/saintamh/canif/
Author: Hervé Saint-Amand
Author-email: canif@saintamh.org
License: UNKNOWN
Platform: UNKNOWN
Classifier: License :: OSI Approved :: MIT License
Classifier: Operating System :: OS Independent
Classifier: Programming Language :: Python :: 3
Classifier: Topic :: Software Development
Classifier: Topic :: Text Processing
Classifier: Topic :: Utilities
